[
    {
        "nome": "fsdaafds",
        "tipo": "Dust",
        "valore_0": 0,
        "valore_1": 0
    },
    {
        "nome": "ff",
        "tipo": "Dust",
        "valore_0": 0,
        "valore_1": 0
    },
    {
        "nome": "afdfadsadfs",
        "tipo": "Dust",
        "valore_0": 0,
        "valore_1": 0
    },
    {
        "nome": "grsger",
        "tipo": "Dust",
        "valore_0": 0,
        "valore_1": 0
    },
    {
        "nome": "grsgerfdg",
        "tipo": "Dust",
        "valore_0": 0,
        "valore_1": 0
    },
    {
        "nome": "grsgerfdgsgfd",
        "tipo": "Dust",
        "valore_0": 0,
        "valore_1": 0
    }
]
